README.md
requirements-dev.txt
requirements.txt
setup.py
exemplary/__init__.py
exemplary/__main__.py
exemplary/interpreter.py
exemplary/parser.py
exemplary.egg-info/PKG-INFO
exemplary.egg-info/SOURCES.txt
exemplary.egg-info/dependency_links.txt
exemplary.egg-info/requires.txt
exemplary.egg-info/top_level.txt