Metadata-Version: 2.1
Name: exemplary
Version: 0.0.7
Summary: Build and test your Python examples
Home-page: https://github.com/jvs/exemplary
Author: jvs
Author-email: vonseg@protonmail.com
License: MIT License
Keywords: documentation,examples
Platform: any
Classifier: Development Status :: 2 - Pre-Alpha
Classifier: License :: OSI Approved :: MIT License
Classifier: Programming Language :: Python
Requires-Python: >=3.6
